mtcli_rvo/__init__.py
mtcli_rvo/commands/__init__.py
mtcli_rvo/commands/rvo.py
mtcli_rvo/conf.py
mtcli_rvo/controllers/__init__.py
mtcli_rvo/controllers/rvo_controller.py
mtcli_rvo/models/__init__.py
mtcli_rvo/models/rvo_model.py
mtcli_rvo/plugin.py
mtcli_rvo/views/__init__.py
mtcli_rvo/views/rvo_view.py
mtcli_rvo-1.0.1.dist-info/entry_points.txt
mtcli_rvo-1.0.1.dist-info/LICENSE
mtcli_rvo-1.0.1.dist-info/METADATA
mtcli_rvo-1.0.1.dist-info/WHEEL
mtcli_rvo-1.0.1.dist-info/RECORD
