Metadata-Version: 2.3
Name: mtcli-rvo
Version: 1.0.1
Summary: Plugin mtcli do indicador RVO (Relative Volume Oscilator)
License: GPL-3.0
Author: Valmir França
Author-email: vfranca3@gmail.com
Requires-Python: >=3.10,<3.14
Classifier: License :: OSI Approved :: GNU General Public License v3 (GPLv3)
Classifier: Programming Language :: Python :: 3
Classifier: Programming Language :: Python :: 3.10
Classifier: Programming Language :: Python :: 3.11
Classifier: Programming Language :: Python :: 3.12
Classifier: Programming Language :: Python :: 3.13
Requires-Dist: click (>=8.3.0,<9.0.0)
Requires-Dist: metatrader5 (>=5.0.5370,<6.0.0)
Requires-Dist: mtcli (>=3.2.0)
Requires-Dist: pandas (>=2.3.3,<3.0.0)
Project-URL: Homepage, https://github.com/vfranca/mtcli-rvo
Project-URL: Repository, https://github.com/vfranca/mtcli-rvo
Project-URL: issues, https://github.com/vfranca/mtcli-rvo/issues
